maliang/table/__init__.py
maliang/table/constants.py
maliang/table/main.py
maliang_table-0.1.0.dist-info/licenses/LICENSE.txt
maliang_table-0.1.0.dist-info/METADATA
maliang_table-0.1.0.dist-info/WHEEL
maliang_table-0.1.0.dist-info/top_level.txt
maliang_table-0.1.0.dist-info/RECORD
