Metadata-Version: 2.4
Name: maliang-table
Version: 0.1.0
Summary: Extension package of maliang for supporting table
Author-email: Xiaokang2022 <2951256653@qq.com>
Maintainer-email: Xiaokang2022 <2951256653@qq.com>
License: MIT License
Project-URL: Bug tracker, https://github.com/Xiaokang2022/maliang-table/issues
Project-URL: Source code, https://github.com/Xiaokang2022/maliang-table
Keywords: tkinter,maliang,table,cross-platform,themed
Classifier: Programming Language :: Python :: 3
Classifier: License :: OSI Approved :: MIT License
Classifier: Operating System :: Microsoft :: Windows
Classifier: Operating System :: POSIX :: Linux
Classifier: Operating System :: MacOS
Classifier: Intended Audience :: Developers
Classifier: Typing :: Typed
Requires-Python: >=3.10
License-File: LICENSE.txt
Requires-Dist: maliang>=3.0.0
Requires-Dist: tksheet>=7.0.0
Dynamic: license-file
